todo_mcp_server/__init__.py
todo_mcp_server/fastmcp_main.py
todo_mcp_server/main.py
todo_mcp_server/protocol.py
todo_mcp_server/server.py
todo_mcp_server-2.1.4.dist-info/METADATA
todo_mcp_server-2.1.4.dist-info/WHEEL
todo_mcp_server-2.1.4.dist-info/entry_points.txt
todo_mcp_server-2.1.4.dist-info/licenses/LICENSE
todo_mcp_server-2.1.4.dist-info/RECORD
