Metadata-Version: 2.4
Name: todo-mcp-server
Version: 2.1.4
Summary: Todo MCP Server powered by FastMCP - 支持多用户的待办事项管理MCP服务器，与 todo-api 同步更新
Project-URL: Homepage, https://github.com/huangzhenxin/todo-mcp-server
Project-URL: Repository, https://github.com/huangzhenxin/todo-mcp-server
Project-URL: Documentation, https://github.com/huangzhenxin/todo-mcp-server#readme
Project-URL: Issues, https://github.com/huangzhenxin/todo-mcp-server/issues
Author-email: huangzhenxin <your-email@example.com>
License: MIT
License-File: LICENSE
Keywords: ai,cursor,mcp,model-context-protocol,todo
Classifier: Development Status :: 4 - Beta
Classifier: Intended Audience :: Developers
Classifier: License :: OSI Approved :: MIT License
Classifier: Programming Language :: Python :: 3
Classifier: Programming Language :: Python :: 3.10
Classifier: Programming Language :: Python :: 3.11
Classifier: Programming Language :: Python :: 3.12
Classifier: Topic :: Software Development :: Libraries :: Python Modules
Requires-Python: >=3.10
Requires-Dist: fastmcp>=2.0.0
Requires-Dist: httpx>=0.24.0
